Melcloudsimple/Melcloudsimple.py
Melcloudsimple/__init__.py
Melcloudsimple/example/Melprog.py
Melcloudsimple/images/2020-04-20.svg
Melcloudsimple/images/power.svg
Melcloudsimple/scripts/2020-04-20
Melcloudsimple/scripts/day.plot
Melcloudsimple/scripts/hist.data
Melcloudsimple/scripts/hist.plot
Melcloudsimple/scripts/hist.sh
Melcloudsimple-0.0.2.dist-info/LICENSE
Melcloudsimple-0.0.2.dist-info/METADATA
Melcloudsimple-0.0.2.dist-info/WHEEL
Melcloudsimple-0.0.2.dist-info/top_level.txt
Melcloudsimple-0.0.2.dist-info/RECORD
