Metadata-Version: 2.1
Name: Melcloudsimple
Version: 0.0.2
Summary: A simple MELCloud access package
Home-page: https://github.com/ferndalehall/Melcloudsimple
Author: John Pickford
Author-email: Melcloudsimple@ferndale-hall.co.uk
License: MIT
Project-URL: Source, https://github.com/ferndalehall/Melcloudsimple
Project-URL: Tracker, https://github.com/ferndalehall/Melcloudsimple/issues
Platform: UNKNOWN
Classifier: Programming Language :: Python :: 3
Classifier: License :: OSI Approved :: MIT License
Classifier: Operating System :: OS Independent
Requires-Python: >=3.6
